random_quote_generator/__init__.py
random_quote_generator/get_quote.py
random_quote_generator/quotes.py
kada_random_quote_generator-0.1.5.dist-info/LICENSE
kada_random_quote_generator-0.1.5.dist-info/WHEEL
kada_random_quote_generator-0.1.5.dist-info/METADATA
kada_random_quote_generator-0.1.5.dist-info/RECORD
