Metadata-Version: 2.1
Name: kada-random-quote-generator
Version: 0.1.5
Summary: Randomly generate programming wisdom quote.
Author: Kada Liao
Author-email: kadaliao@gmail.com
Requires-Python: >=3.9,<4.0
Classifier: Programming Language :: Python :: 3
Classifier: Programming Language :: Python :: 3.9
